cdma/__init__.py
cdma/display/__init__.py
cdma/display/ipy_stack_viewer.py
cdma/io.py
cdma/misc/clean_jetbrains_cache.sh
cdma/mock_data/__init__.py
cdma/mock_data/volumes.py
cdma/styling/cdma_cmaps.py
cdma/styling/color_utils.py
cdma/styling/napari_themes.py
cdma/utils.py
cdma-0.0.6.dist-info/WHEEL
cdma-0.0.6.dist-info/METADATA
cdma-0.0.6.dist-info/RECORD
