Metadata-Version: 2.4
Name: cdma
Version: 0.0.6
Summary: A collection of utilities related to processing 3D volumetric data and the CDMA group of Rostock University.
Keywords: 
Author: Malte Bruhn
Author-email: Malte Bruhn <malte.bruhn@uni-rostock.de>
License-Expression: MIT
Classifier: Development Status :: 3 - Alpha
Classifier: Programming Language :: Python
Requires-Dist: dask[array]>=2025.9.0
Requires-Dist: ipython>=9.5.0
Requires-Dist: ipywidgets>=8.1.7
Requires-Dist: joblib>=1.5.2
Requires-Dist: napari>=0.6.4
Requires-Dist: notebook>=7.4.5
Requires-Dist: numpy>=2.3.3
Requires-Dist: pillow>=11.3.0
Requires-Dist: scikit-image>=0.25.2
Requires-Dist: seaborn>=0.13.2
Maintainer: Malte Bruhn
Maintainer-email: Malte Bruhn <malte.bruhn@uni-rostock.de>
Requires-Python: >=3.11
Project-URL: Repository, https://gitlab.uni-rostock.de/msf-cdma/cdma-utils.git
